spotopt/__init__.py
spotopt/_constants.py
spotopt/_exceptions.py
spotopt/_features.py
spotopt/_logging.py
spotopt/_types.py
spotopt/_utils.py
spotopt/_validation.py
spotopt/model.py
spotopt-0.1.0.dist-info/licenses/LICENSE
spotopt-0.1.0.dist-info/METADATA
spotopt-0.1.0.dist-info/WHEEL
spotopt-0.1.0.dist-info/top_level.txt
spotopt-0.1.0.dist-info/RECORD
