Metadata-Version: 2.4
Name: spotopt
Version: 0.1.0
Summary: spotopt: A Python library for converting deterministic forecasts into probabilistic ones.
Author: Raik Becker
License-Expression: MIT
Project-URL: repository, https://github.com/spotopt/spotopt-probabilistic
Project-URL: homepage, https://github.com/spotopt/spotopt-probabilistic
Project-URL: documentation, https://github.com/spotopt/spotopt-probabilistic#readme
Keywords: forecasting,probabilistic,quantile-regression
Classifier: Development Status :: 5 - Production/Stable
Classifier: Programming Language :: Python :: 3.11
Classifier: Programming Language :: Python :: 3.12
Classifier: Programming Language :: Python :: 3.13
Requires-Python: >=3.11
License-File: LICENSE
Requires-Dist: pandas>=2.3.0
Requires-Dist: pytz>=2025.0
Requires-Dist: scikit-learn>=1.6.0
Dynamic: license-file
